[
    {
        "userId": "Gladyce.Kuhic",
        "userName": "Gladyce Kuhic",
        "email": "Gladyce_Kuhic18@example.org"
    },
    {
        "userId": "Nikki.Sauer69",
        "userName": "Nikki Sauer",
        "email": "Nikki_Sauer81@example.com"
    },
    {
        "userId": "Tara_Heidenreich",
        "userName": "Tara Heidenreich",
        "email": "Tara_Heidenreich@example.net"
    },
    {
        "userId": "Karl_Konopelski",
        "userName": "Karl Konopelski",
        "email": "Karl85@example.net"
    },
    {
        "userId": "Conrad.Adams",
        "userName": "Conrad Adams",
        "email": "Conrad45@example.org"
    },
    {
        "userId": "Isaiah.Braun58",
        "userName": "Isaiah Braun",
        "email": "Isaiah_Braun65@example.com"
    },
    {
        "userId": "Kole_Veum47",
        "userName": "Kole Veum",
        "email": "Kole_Veum@example.net"
    },
    {
        "userId": "Torrance94",
        "userName": "Torrance Steuber",
        "email": "Torrance_Steuber@example.com"
    },
    {
        "userId": "Lenny_Farrell62",
        "userName": "Lenny Farrell",
        "email": "Lenny.Farrell41@example.com"
    },
    {
        "userId": "Kasey0",
        "userName": "Kasey Heller",
        "email": "Kasey_Heller43@example.org"
    },
    {
        "userId": "Carson_Kautzer95",
        "userName": "Carson Kautzer",
        "email": "Carson_Kautzer1@example.org"
    },
    {
        "userId": "Stephanie70",
        "userName": "Stephanie Wolf",
        "email": "Stephanie97@example.org"
    },
    {
        "userId": "Arthur1",
        "userName": "Arthur Schroeder",
        "email": "Arthur87@example.org"
    },
    {
        "userId": "Brain.Lemke33",
        "userName": "Brain Lemke",
        "email": "Brain_Lemke75@example.com"
    },
    {
        "userId": "Laurianne_Roob4",
        "userName": "Laurianne Roob",
        "email": "Laurianne50@example.net"
    },
    {
        "userId": "Meagan.Rath",
        "userName": "Meagan Rath",
        "email": "Meagan_Rath14@example.net"
    },
    {
        "userId": "Dejah81",
        "userName": "Dejah Parisian",
        "email": "Dejah_Parisian@example.org"
    },
    {
        "userId": "Luna45",
        "userName": "Luna Treutel",
        "email": "Luna_Treutel79@example.org"
    },
    {
        "userId": "Dexter71",
        "userName": "Dexter Casper",
        "email": "Dexter.Casper@example.com"
    },
    {
        "userId": "Elisha.Johnson84",
        "userName": "Elisha Johnson",
        "email": "Elisha_Johnson99@example.org"
    },
    {
        "userId": "Mariah21",
        "userName": "Mariah Wisoky",
        "email": "Mariah61@example.net"
    },
    {
        "userId": "Alysha_Runte43",
        "userName": "Alysha Runte",
        "email": "Alysha_Runte9@example.net"
    },
    {
        "userId": "Brando11",
        "userName": "Brando Stoltenberg",
        "email": "Brando2@example.net"
    },
    {
        "userId": "Lennie.Kuhic",
        "userName": "Lennie Kuhic",
        "email": "Lennie60@example.com"
    },
    {
        "userId": "Noemi_Mraz",
        "userName": "Noemi Mraz",
        "email": "Noemi4@example.com"
    },
    {
        "userId": "Cleora_Schmitt93",
        "userName": "Cleora Schmitt",
        "email": "Cleora_Schmitt@example.net"
    },
    {
        "userId": "Anita81",
        "userName": "Anita Larson",
        "email": "Anita22@example.org"
    },
    {
        "userId": "Pat_Torp18",
        "userName": "Pat Torp",
        "email": "Pat.Torp@example.com"
    },
    {
        "userId": "Aaron.Schuster80",
        "userName": "Aaron Schuster",
        "email": "Aaron_Schuster@example.net"
    },
    {
        "userId": "Morton_Pollich",
        "userName": "Morton Pollich",
        "email": "Morton79@example.net"
    },
    {
        "userId": "Cory_Witting",
        "userName": "Cory Witting",
        "email": "Cory46@example.net"
    },
    {
        "userId": "Ova_Bartoletti97",
        "userName": "Ova Bartoletti",
        "email": "Ova.Bartoletti@example.net"
    },
    {
        "userId": "Michelle_Howe",
        "userName": "Michelle Howe",
        "email": "Michelle_Howe56@example.net"
    },
    {
        "userId": "Ena.Kuhn",
        "userName": "Ena Kuhn",
        "email": "Ena.Kuhn35@example.net"
    },
    {
        "userId": "Drake.Hagenes45",
        "userName": "Drake Hagenes",
        "email": "Drake.Hagenes@example.net"
    },
    {
        "userId": "Susanna.Jaskolski",
        "userName": "Susanna Jaskolski",
        "email": "Susanna.Jaskolski@example.org"
    },
    {
        "userId": "Erica_Davis78",
        "userName": "Erica Davis",
        "email": "Erica_Davis41@example.org"
    },
    {
        "userId": "Milton_Willms49",
        "userName": "Milton Willms",
        "email": "Milton0@example.net"
    },
    {
        "userId": "Dee_Schamberger",
        "userName": "Dee Schamberger",
        "email": "Dee_Schamberger@example.org"
    },
    {
        "userId": "Clotilde0",
        "userName": "Clotilde Lindgren",
        "email": "Clotilde.Lindgren30@example.net"
    },
    {
        "userId": "Myles.Robel",
        "userName": "Myles Robel",
        "email": "Myles.Robel61@example.com"
    },
    {
        "userId": "Mireya_Runolfsson41",
        "userName": "Mireya Runolfsson",
        "email": "Mireya72@example.com"
    },
    {
        "userId": "Bulah.Moen1",
        "userName": "Bulah Moen",
        "email": "Bulah53@example.net"
    },
    {
        "userId": "Jaleel.Swift",
        "userName": "Jaleel Swift",
        "email": "Jaleel.Swift@example.org"
    },
    {
        "userId": "Priscilla50",
        "userName": "Priscilla King",
        "email": "Priscilla.King@example.com"
    },
    {
        "userId": "Verna_Botsford",
        "userName": "Verna Botsford",
        "email": "Verna_Botsford88@example.com"
    },
    {
        "userId": "Hayley.Herzog",
        "userName": "Hayley Herzog",
        "email": "Hayley_Herzog29@example.com"
    },
    {
        "userId": "Landen.Ziemann",
        "userName": "Landen Ziemann",
        "email": "Landen14@example.net"
    },
    {
        "userId": "Lance_Gutmann94",
        "userName": "Lance Gutmann",
        "email": "Lance.Gutmann@example.net"
    },
    {
        "userId": "Rudy.Olson87",
        "userName": "Rudy Olson",
        "email": "Rudy.Olson81@example.com"
    },
    {
        "userId": "Desiree36",
        "userName": "Desiree Hirthe",
        "email": "Desiree.Hirthe@example.net"
    },
    {
        "userId": "Dana_Grant82",
        "userName": "Dana Grant",
        "email": "Dana9@example.com"
    },
    {
        "userId": "Dorthy.Schaefer44",
        "userName": "Dorthy Schaefer",
        "email": "Dorthy73@example.com"
    },
    {
        "userId": "Wava.Kohler",
        "userName": "Wava Kohler",
        "email": "Wava38@example.com"
    },
    {
        "userId": "Agnes_Stanton93",
        "userName": "Agnes Stanton",
        "email": "Agnes51@example.org"
    },
    {
        "userId": "Garnett_Little70",
        "userName": "Garnett Little",
        "email": "Garnett50@example.com"
    },
    {
        "userId": "Lawrence_Bailey36",
        "userName": "Lawrence Bailey",
        "email": "Lawrence41@example.net"
    },
    {
        "userId": "Felicity.Hahn55",
        "userName": "Felicity Hahn",
        "email": "Felicity_Hahn@example.com"
    },
    {
        "userId": "Madyson_Fritsch",
        "userName": "Madyson Fritsch",
        "email": "Madyson.Fritsch@example.com"
    },
    {
        "userId": "Hershel_Haley",
        "userName": "Hershel Haley",
        "email": "Hershel_Haley5@example.net"
    },
    {
        "userId": "Bridgette54",
        "userName": "Bridgette Hagenes",
        "email": "Bridgette_Hagenes@example.net"
    },
    {
        "userId": "Savanna.Gulgowski",
        "userName": "Savanna Gulgowski",
        "email": "Savanna39@example.org"
    },
    {
        "userId": "Landen28",
        "userName": "Landen Durgan",
        "email": "Landen_Durgan@example.org"
    },
    {
        "userId": "Brown_Harber",
        "userName": "Brown Harber",
        "email": "Brown11@example.com"
    },
    {
        "userId": "Mariano57",
        "userName": "Mariano Marks",
        "email": "Mariano36@example.net"
    },
    {
        "userId": "Helena28",
        "userName": "Helena Schoen",
        "email": "Helena39@example.org"
    },
    {
        "userId": "Lela.Mraz",
        "userName": "Lela Mraz",
        "email": "Lela.Mraz33@example.com"
    },
    {
        "userId": "Berenice_Hegmann64",
        "userName": "Berenice Hegmann",
        "email": "Berenice.Hegmann@example.org"
    },
    {
        "userId": "Margaret.Gerlach",
        "userName": "Margaret Gerlach",
        "email": "Margaret97@example.org"
    },
    {
        "userId": "Casandra_Miller",
        "userName": "Casandra Miller",
        "email": "Casandra.Miller@example.net"
    },
    {
        "userId": "Tina49",
        "userName": "Tina Schiller",
        "email": "Tina.Schiller82@example.com"
    },
    {
        "userId": "Cleo.Windler39",
        "userName": "Cleo Windler",
        "email": "Cleo49@example.com"
    },
    {
        "userId": "Yadira_Jakubowski52",
        "userName": "Yadira Jakubowski",
        "email": "Yadira_Jakubowski@example.net"
    },
    {
        "userId": "Deja.Bergnaum",
        "userName": "Deja Bergnaum",
        "email": "Deja_Bergnaum6@example.net"
    },
    {
        "userId": "Edison.Wintheiser",
        "userName": "Edison Wintheiser",
        "email": "Edison_Wintheiser@example.net"
    },
    {
        "userId": "Benjamin6",
        "userName": "Benjamin Cormier",
        "email": "Benjamin_Cormier@example.net"
    },
    {
        "userId": "Retha.Gutmann",
        "userName": "Retha Gutmann",
        "email": "Retha65@example.net"
    },
    {
        "userId": "Pauline.Hackett",
        "userName": "Pauline Hackett",
        "email": "Pauline_Hackett11@example.org"
    },
    {
        "userId": "Shanelle.White",
        "userName": "Shanelle White",
        "email": "Shanelle_White@example.org"
    },
    {
        "userId": "Jaquelin.McDermott54",
        "userName": "Jaquelin McDermott",
        "email": "Jaquelin.McDermott@example.net"
    },
    {
        "userId": "Billy_Jast32",
        "userName": "Billy Jast",
        "email": "Billy.Jast@example.org"
    },
    {
        "userId": "Herman.Hermiston",
        "userName": "Herman Hermiston",
        "email": "Herman69@example.com"
    },
    {
        "userId": "Daphne15",
        "userName": "Daphne McGlynn",
        "email": "Daphne39@example.net"
    },
    {
        "userId": "Felix_Gleichner",
        "userName": "Felix Gleichner",
        "email": "Felix_Gleichner@example.com"
    },
    {
        "userId": "Asha.Treutel",
        "userName": "Asha Treutel",
        "email": "Asha33@example.org"
    },
    {
        "userId": "Name.Spencer",
        "userName": "Name Spencer",
        "email": "Name73@example.net"
    },
    {
        "userId": "Viviane87",
        "userName": "Viviane Zulauf",
        "email": "Viviane_Zulauf@example.com"
    },
    {
        "userId": "Delpha.Considine39",
        "userName": "Delpha Considine",
        "email": "Delpha_Considine@example.com"
    },
    {
        "userId": "Penelope.Feest",
        "userName": "Penelope Feest",
        "email": "Penelope82@example.net"
    },
    {
        "userId": "Zackery14",
        "userName": "Zackery Nicolas",
        "email": "Zackery_Nicolas@example.com"
    },
    {
        "userId": "Griffin.Ortiz",
        "userName": "Griffin Ortiz",
        "email": "Griffin.Ortiz50@example.org"
    },
    {
        "userId": "Elody88",
        "userName": "Elody Kunde",
        "email": "Elody.Kunde61@example.com"
    },
    {
        "userId": "Armando_Schulist9",
        "userName": "Armando Schulist",
        "email": "Armando_Schulist@example.net"
    },
    {
        "userId": "Nolan.Kessler36",
        "userName": "Nolan Kessler",
        "email": "Nolan3@example.net"
    },
    {
        "userId": "Bertram91",
        "userName": "Bertram Effertz",
        "email": "Bertram92@example.net"
    },
    {
        "userId": "Mckayla.Beer80",
        "userName": "Mckayla Beer",
        "email": "Mckayla92@example.net"
    },
    {
        "userId": "Darius.Schoen",
        "userName": "Darius Schoen",
        "email": "Darius14@example.net"
    },
    {
        "userId": "Dana.Denesik",
        "userName": "Dana Denesik",
        "email": "Dana.Denesik71@example.com"
    },
    {
        "userId": "Jaquan_Walter",
        "userName": "Jaquan Walter",
        "email": "Jaquan.Walter@example.net"
    },
    {
        "userId": "Lucinda_Feeney",
        "userName": "Lucinda Feeney",
        "email": "Lucinda.Feeney@example.net"
    }
]